nonebot_plugin_bread_shop/__init__.py
nonebot_plugin_bread_shop/bread_event.py
nonebot_plugin_bread_shop/bread_handle.py
nonebot_plugin_bread_shop/bread_operate.py
nonebot_plugin_bread_shop/config.py
nonebot_plugin_bread_shop-0.1.14.dist-info/LICENSE
nonebot_plugin_bread_shop-0.1.14.dist-info/METADATA
nonebot_plugin_bread_shop-0.1.14.dist-info/WHEEL
nonebot_plugin_bread_shop-0.1.14.dist-info/RECORD
