Metadata-Version: 2.1
Name: nonebot-plugin-bread-shop
Version: 0.1.14
Summary: nobebot2面包店插件
Home-page: https://github.com/Mai-icy/nonebot-plugin-bread-shop
License: MIT
Keywords: nonebot,nonebot2,qqbot
Author: Mai Icy
Author-email: maiicy@Foxmail.com
Requires-Python: >=3.7.7,<4.0.0
Classifier: License :: OSI Approved :: MIT License
Classifier: Programming Language :: Python :: 3
Classifier: Programming Language :: Python :: 3.8
Classifier: Programming Language :: Python :: 3.9
Classifier: Programming Language :: Python :: 3.10
Classifier: Programming Language :: Python :: 3.11
Requires-Dist: nonebot-adapter-onebot (>=2.0.0-beta.1,<3.0.0)
Requires-Dist: nonebot2 (>=2.0.0-beta.2,<3.0.0)
Project-URL: Repository, https://github.com/Mai-icy/nonebot-plugin-bread-shop
